linformer_pytorch/__init__.py
linformer_pytorch/linformer_pytorch.py
linformer_pytorch/padder.py
linformer_pytorch/visualizer.py
linformer_pytorch-0.19.3.dist-info/LICENSE
linformer_pytorch-0.19.3.dist-info/METADATA
linformer_pytorch-0.19.3.dist-info/WHEEL
linformer_pytorch-0.19.3.dist-info/top_level.txt
linformer_pytorch-0.19.3.dist-info/RECORD
