Metadata-Version: 2.1
Name: linformer-pytorch
Version: 0.19.3
Summary: An implementation of the Linformer in Pytorch
Home-page: https://github.com/tatp22/linformer-pytorch
Author: Peter Tatkowski
Author-email: tatp22@gmail.com
License: UNKNOWN
Keywords: transformers,attention,deep learning,artificial intelligence,sparse attention
Platform: UNKNOWN
Classifier: Programming Language :: Python :: 3
Classifier: License :: OSI Approved :: MIT License
Classifier: Topic :: Scientific/Engineering :: Artificial Intelligence
Requires-Dist: torch
Requires-Dist: matplotlib
